classiloom/__init__.py
classiloom/cli.py
classiloom/config.py
classiloom/data.py
classiloom/gemini.py
classiloom/metrics.py
classiloom/models.py
classiloom/trainer.py
classiloom/utils.py
classiloom-1.0.0.dist-info/METADATA
classiloom-1.0.0.dist-info/WHEEL
classiloom-1.0.0.dist-info/entry_points.txt
classiloom-1.0.0.dist-info/top_level.txt
classiloom-1.0.0.dist-info/RECORD
